{"chunk_definitions":[{"row":22,"row_count":1,"visible":true,"expansion_state":0,"options":{"engine":"r","message":false,"label":"unnamed-chunk-160"},"document_id":"B816F309","chunk_id":"cg733cimn4q1g","chunk_label":"unnamed-chunk-1"},{"row":44,"row_count":1,"visible":true,"expansion_state":0,"options":{"engine":"r","label":"unnamed-chunk-169"},"document_id":"B816F309","chunk_id":"cepqxqjnov4ye","chunk_label":"unnamed-chunk-2"},{"row":56,"row_count":1,"visible":true,"expansion_state":0,"options":{"engine":"r","label":"unnamed-chunk-177"},"document_id":"B816F309","chunk_id":"c13bvx582q5m5","chunk_label":"unnamed-chunk-3"},{"row":72,"row_count":1,"visible":true,"expansion_state":0,"options":{"engine":"r","label":"unnamed-chunk-178"},"document_id":"B816F309","chunk_id":"czlueskkrhgaj","chunk_label":"unnamed-chunk-4"},{"row":78,"row_count":1,"visible":true,"expansion_state":0,"options":{"engine":"r","label":"unnamed-chunk-188"},"document_id":"B816F309","chunk_id":"csongsgz2ghvl","chunk_label":"unnamed-chunk-5"},{"row":83,"row_count":1,"visible":true,"expansion_state":0,"options":{"engine":"r","label":"unnamed-chunk-189"},"document_id":"B816F309","chunk_id":"cj16eyug46dhg","chunk_label":"unnamed-chunk-6"},{"row":91,"row_count":1,"visible":true,"expansion_state":0,"options":{"engine":"r","label":"unnamed-chunk-190"},"document_id":"B816F309","chunk_id":"c1o3q25sceajy","chunk_label":"unnamed-chunk-7"},{"row":101,"row_count":1,"visible":true,"expansion_state":0,"options":{"engine":"r","message":true,"label":"unnamed-chunk-192"},"document_id":"B816F309","chunk_id":"cupl0tr5t7l65","chunk_label":"unnamed-chunk-8"}],"doc_write_time":1669788110,"chunk_rendered_width":700}